EmojiCloud
