Metadata-Version: 2.1
Name: EmojiCloud
Version: 0.2.0
Summary: EmojiCloud: a Tool for Emoji Cloud Visualization
Home-page: https://github.com/YunheFeng/EmojiCloud
Author: Yunhe Feng
Author-email: yunhefengit@gmail.com
Project-URL: Bug Tracker, https://github.com/YunheFeng/EmojiCloud/issues
Classifier: Programming Language :: Python :: 3
Classifier: License :: OSI Approved :: MIT License
Classifier: Operating System :: OS Independent
Requires-Python: >=3.6
License-File: LICENSE
